{
  "data": {
    "amount": "1500.00",
    "currency": "USD",
    "decision": "cleared",
    "description": "Monthly rent payment",
    "destination_account": "ACC-2001",
    "fraud_review": false,
    "fraud_signals": [],
    "metadata": {
      "channel": "online",
      "country": "US"
    },
    "pipeline_order_used": [
      "transaction_validator",
      "fraud_detector",
      "compliance_checker"
    ],
    "reason": [],
    "requires_report": false,
    "risk_score": 0,
    "source_account": "ACC-1001",
    "status": "cleared",
    "timestamp": "2026-03-16T09:00:00Z",
    "transaction_id": "TXN001",
    "transaction_type": "transfer"
  },
  "message_id": "644c9b76-7dc1-4731-b01a-3c25b1479a89",
  "message_type": "transaction",
  "source_agent": "compliance_checker",
  "target_agent": "compliance_checker",
  "timestamp": "2026-07-09T17:06:00Z"
}