{
  "data": {
    "amount": "500.00",
    "currency": "EUR",
    "decision": "cleared",
    "description": "Invoice #4471",
    "destination_account": "ACC-5500",
    "fraud_review": false,
    "fraud_signals": [
      "off_hours",
      "cross_border"
    ],
    "metadata": {
      "channel": "api",
      "country": "DE"
    },
    "pipeline_order_used": [
      "transaction_validator",
      "fraud_detector",
      "compliance_checker"
    ],
    "reason": [],
    "requires_report": false,
    "risk_score": 35,
    "source_account": "ACC-1004",
    "status": "cleared",
    "timestamp": "2026-03-16T02:47:00Z",
    "transaction_id": "TXN004",
    "transaction_type": "transfer"
  },
  "message_id": "4a1be712-da25-4a47-a170-55db4d34a4f6",
  "message_type": "transaction",
  "source_agent": "compliance_checker",
  "target_agent": "compliance_checker",
  "timestamp": "2026-07-09T17:06:00Z"
}